delbot
