Metadata-Version: 2.1
Name: delbot
Version: 0.4.0
Summary: A service status blog for SaaS applications
Home-page: https://git.steadman.io/podiant/delbot
Author: Mark Steadman
Author-email: mark@podiant.co
License: MIT
Keywords: delbot
Platform: UNKNOWN
Classifier: Development Status :: 3 - Alpha
Classifier: Framework :: Django :: 1.11
Classifier: Intended Audience :: Developers
Classifier: License :: OSI Approved :: BSD License
Classifier: Natural Language :: English
Classifier: Programming Language :: Python :: 3
Classifier: Programming Language :: Python :: 3.4
Classifier: Programming Language :: Python :: 3.5
Classifier: Programming Language :: Python :: 3.6
